<?xml version="1.0" encoding="UTF-8"?>
<monster name="Goblin Assassin" nameDescription="a goblin assassin" race="blood" experience="180" speed="250" manacost="0">
    <health now="225" max="225"/>
    <look type="61" corpse="3065"/>
    <targetchange interval="4000" chance="10"/>
    <strategy attack="100" defense="5"/>
    <flags>
        <flag summonable="0"/>
        <flag attackable="1"/>
        <flag hostile="1"/>
        <flag illusionable="1"/>
        <flag convinceable="0"/>
        <flag pushable="0"/>
        <flag canpushitems="1"/>
        <flag canpushcreatures="1"/>
        <flag targetdistance="1"/>
        <flag staticattackthreat="95"/>
    </flags>
    <attacks>
        <attack name="melee" interval="2000" min="-20" max="-40"/>
        <attack name="physical" interval="2200" chance="30" range="7" min="-15" max="-35"/>
        <attack name="speed" interval="3000" chance="20" speedchange="-150" duration="8000"/>
    </attacks>
    <defenses armor="12" defense="18"/>
    <voices interval="5000" chance="10">
        <voice sentence="You will not escape!"/>
        <voice sentence="*hiss*"/>
        <voice sentence="Die quickly!"/>
    </voices>
    <loot>
        <item id="2148" countmax="18" chance="50000"/>
        <item id="2378" chance="25000"/>
        <item id="2397" chance="20000"/>
        <item id="2666" chance="15000"/>
    </loot>
</monster>